Metadata-Version: 1.1
Name: taggd
Version: 0.3.6
Summary: Bioinformatics genetic barcode demultiplexing
Home-page: https://github.com/SpatialTranscriptomicsResearch/taggd
Author: Joel Sjostrand, Jose Fernandez
Author-email: joel.sjostrand@scilifelab.se, jose.fernandez.navarro@scilifelab.se
License: Open BSD
Download-URL: https://github.com/SpatialTranscriptomicsResearch/taggd/0.3.2
Keywords: bioinformatics,demultiplexing
Platform: UNKNOWN
